DAY 02/Binary to Gray/binary_gray_d.v
//design
module binary_gray( input [3:0]binary, output [3:0]gray );
assign gray [3] = binary [3] ;
assign gray [2] = binary [3] ^ binary [2];
assign gray [1] = binary [2] ^ binary [1];
assign gray [0] = binary [1] ^ binary [0];
endmodule

DAY 02/Binary to Gray/binary_gray.v
//test bench
module tb_binary_gray;
reg [3:0]binary;
wire [3:0]gray;
//dut
binary_gray dut(.binary(binary),.gray(gray));
initial begin
$monitor("|  binary=%b  |  gray=%b  |  time=%0t   ",binary,gray,$time);
$dumpfile("binary_gray.vcd");
$dumpvars();

binary = 4'b0000;
#10;
binary = 4'b0001;
#10;
binary = 4'b0010;
#10;
binary = 4'b0011;
#10;
binary = 4'b0100;
#10;
binary = 4'b0101;
#10;
binary = 4'b0110;
#10;
binary = 4'b0111;
#10;
binary = 4'b1000;
#10;
binary = 4'b1001;
#10;
binary = 4'b1010;
#10;
binary = 4'b1011;
#10;
binary = 4'b1100;
#10;
binary = 4'b1101;
#10;
binary = 4'b1110;
#10;
binary = 4'b1111;
#10;
$finish;
end
endmodule

DAY 02/Binary to Gray/binary_gray.vcd
$date
	Fri Dec 12 04:48:06 2025
$end
$version
	Icarus Verilog
$end
$timescale
	1s
$end
$scope module tb_binary_gray $end
$var wire 4 ! gray [3:0] $end
$var reg 4 " binary [3:0] $end
$scope module dut $end
$var wire 4 # binary [3:0] $end
$var wire 4 $ gray [3:0] $end
$upscope $end
$upscope $end
$enddefinitions $end
$comment Show the parameter values. $end
$dumpall
$end
#0
$dumpvars
b0 $
b0 #
b0 "
b0 !
$end
#10
b1 !
b1 $
b1 "
b1 #
#20
b11 !
b11 $
b10 "
b10 #
#30
b10 !
b10 $
b11 "
b11 #
#40
b110 !
b110 $
b100 "
b100 #
#50
b111 !
b111 $
b101 "
b101 #
#60
b101 !
b101 $
b110 "
b110 #
#70
b100 !
b100 $
b111 "
b111 #
#80
b1100 !
b1100 $
b1000 "
b1000 #
#90
b1101 !
b1101 $
b1001 "
b1001 #
#100
b1111 !
b1111 $
b1010 "
b1010 #
#110
b1110 !
b1110 $
b1011 "
b1011 #
#120
b1010 !
b1010 $
b1100 "
b1100 #
#130
b1011 !
b1011 $
b1101 "
b1101 #
#140
b1001 !
b1001 $
b1110 "
b1110 #
#150
b1000 !
b1000 $
b1111 "
b1111 #
