DAY 03/Decoder_3to8/3to8_decoder.v
//design
module decoder_3to8 (input [2:0] in , output[7:0] out);
assign out[0] = ~in[2] & ~in[1] & ~in[0];
assign out[1] = ~in[2] & ~in[1] &  in[0];
assign out[2] = ~in[2] &  in[1] & ~in[0];
assign out[3] = ~in[2] &  in[1] &  in[0];
assign out[4] =  in[2] & ~in[1] & ~in[0];
assign out[5] =  in[2] & ~in[1] &  in[0];
assign out[6] =  in[2] &  in[1] & ~in[0];
assign out[7] =  in[2] &  in[1] &  in[0];
endmodule

//test bench
module tb_decoder_3to8; 
reg[2:0] in;
wire[7:0] out;
//dut
 decoder_3to8 dut
 (in,out); 
 initial begin
	 $monitor("time=%0t  | in=%b | out=%b |",$time,in,out);
	 $dumpfile("decoder_3to8.vcd");
	 $dumpvars();

	 in = 3'b000 ;
	 #10
	 in = 3'b001 ;
	 #10
	 in = 3'b010 ;
	 #10
	 in = 3'b011 ;
	 #10
	 in = 3'b100 ;
	 #10
	 in = 3'b101 ;
	 #10
	 in = 3'b110 ;
	 #10
	 in = 3'b111 ;
	 #10
	 $finish;
 end
 endmodule

DAY 03/decoder_3to8.vcd
$date
	Fri Dec  5 10:15:52 2025
$end
$version
	Icarus Verilog
$end
$timescale
	1s
$end
$scope module tb_decoder_3to8 $end
$var wire 8 ! out [7:0] $end
$var reg 3 " in [2:0] $end
$scope module dut $end
$var wire 3 # in [2:0] $end
$var wire 8 $ out [7:0] $end
$upscope $end
$upscope $end
$enddefinitions $end
$comment Show the parameter values. $end
$dumpall
$end
#0
$dumpvars
b1 $
b0 #
b0 "
b1 !
$end
#10
b10 !
b10 $
b1 "
b1 #
#20
b100 !
b100 $
b10 "
b10 #
#30
b1000 !
b1000 $
b11 "
b11 #
#40
b10000 !
b10000 $
b100 "
b100 #
#50
b100000 !
b100000 $
b101 "
b101 #
#60
b1000000 !
b1000000 $
b110 "
b110 #
#70
b10000000 !
b10000000 $
b111 "
b111 #
