DAY 03/83_encoder.v
//design
module encoder_8to3 (input [7:0] in , output[2:0] out);
assign out = (in[0]) ? 3'b000 :
             (in[1]) ? 3'b001 :
             (in[2]) ? 3'b010 :
             (in[3]) ? 3'b011 :
             (in[4]) ? 3'b100 :
             (in[5]) ? 3'b101 :
             (in[6]) ? 3'b110 :
             (in[7]) ? 3'b111 :
	     3'bxxx;
endmodule

//test bench
module tb_encoder_8to3;
reg [7:0] in ;
wire [2:0] out ;
//dut
 encoder_8to3 dut 
 (in ,out);
 initial begin
	 $monitor("$time=%t  | in=%b | out=%b |",$time,in,out);
	 $dumpfile( "encoder_8to3.vcd");
	 $dumpvars (0, tb_encoder_8to3);

	 in = 8'b00000001; #10;
	 in = 8'b00000010; #10;
	 in = 8'b00000100; #10;
	 in = 8'b00001000; #10;
	 in = 8'b00010000; #10;
	 in = 8'b00100000; #10;
	 in = 8'b01000000; #10;
	 in = 8'b10000000; #10;
	 $finish;
 end
 endmodule

DAY 03/encoder_8to3.vcd
$date
	Fri Dec  5 11:20:11 2025
$end
$version
	Icarus Verilog
$end
$timescale
	1s
$end
$scope module tb_encoder_8to3 $end
$var wire 3 ! out [2:0] $end
$var reg 8 " in [7:0] $end
$scope module dut $end
$var wire 8 # in [7:0] $end
$var wire 3 $ out [2:0] $end
$upscope $end
$upscope $end
$enddefinitions $end
$comment Show the parameter values. $end
$dumpall
$end
#0
$dumpvars
b0 $
b1 #
b1 "
b0 !
$end
#10
b1 !
b1 $
b10 "
b10 #
#20
b10 !
b10 $
b100 "
b100 #
#30
b11 !
b11 $
b1000 "
b1000 #
#40
b100 !
b100 $
b10000 "
b10000 #
#50
b101 !
b101 $
b100000 "
b100000 #
#60
b110 !
b110 $
b1000000 "
b1000000 #
#70
b111 !
b111 $
b10000000 "
b10000000 #
